DiscordStatusPy/__init__.py
DiscordStatusPy/client.py
DiscordStatusPy/urls.py
DiscordStatusPy-0.0.1.dist-info/LICENSE
DiscordStatusPy-0.0.1.dist-info/METADATA
DiscordStatusPy-0.0.1.dist-info/WHEEL
DiscordStatusPy-0.0.1.dist-info/top_level.txt
DiscordStatusPy-0.0.1.dist-info/RECORD
