Metadata-Version: 2.1
Name: DiscordStatusPy
Version: 0.0.1
Summary: Async API wrapper around discordstatus.com
Home-page: https://github.com/Booplicate/DiscordStatusPy
Author: Booplicate
License: UNKNOWN
Project-URL: Bug Tracker, https://github.com/Booplicate/DiscordStatusPy/issues
Platform: UNKNOWN
Classifier: Programming Language :: Python :: 3.9
Classifier: License :: OSI Approved :: GNU Affero General Public License v3
Classifier: Operating System :: OS Independent
Requires-Python: >=3.9.6
License-File: LICENSE
Requires-Dist: aiohttp (>=3.7.4)
